{"file:///C:/Users/Stage4000/Documents/larrypotterlandscape.com":{"assets/images/hashes.json":"KpjgiA7Udl679HtaCkfisw==","assets/images/imageedit-1.png":"b6baOgAAfh4/X8c/zmosvA==","assets/images/dsc02218-595x446.jpg":"72iGlKCvgXAhsMvTymobEA==","assets/images/mbr-595x397.jpg":"L4RIHfFPsaW2pv0v8grNRg==","assets/images/dsc01039-2-2000x1125.jpg":"wRHtKCsMEaDNyfHki4EpVQ==","assets/images/dsc01034-1462x823.jpg":"GgswWhreLlmcjSFHAqL72A==","assets/images/dsc00378-2000x1125.jpg":"LOgftLc/3qI0CtzLaWv4rw==","assets/web/assets/jquery/jquery.min.js":"3F5/GMjTasHT1HU6h8mNCg==","assets/bootstrap/css/bootstrap.min.css":"gWrw7d07SCLCdWInx+e37g==","assets/bootstrap/css/bootstrap-grid.min.css":"ZpQEaHtj4rsdGDC9wDZdfg==","assets/bootstrap/css/bootstrap-reboot.min.css":"eMZwSLVvZudwLH9xiGj50w==","assets/bootstrap/js/bootstrap.min.js":"AtIjOT4AwnPv3LGt6PT4sQ==","assets/popper/popper.min.js":"NiE4ESlZe/NNSKniYj4FyQ==","assets/tether/tether.min.css":"YhVaOUjL8Xsb9LQHyQq4Tw==","assets/tether/tether.min.js":"PlC291/0Eo8keLHUT4D9+w==","assets/theme/css/style.css":"TToltBSF6Y4a0NZLoX3hQw==","assets/theme/js/script.js":"pUdbD8Zr3jRnTjxr/+7UQA==","assets/smoothscroll/smooth-scroll.js":"e15+ccLIeWb2A3ZYIotPaw==","assets/dropdown/css/style.css":"s+S8lVC62P0BWFtgHpaNFA==","assets/dropdown/js/nav-dropdown.js":"j5pq4WKLRnihd7IVVkQkJg==","assets/dropdown/js/navbar-dropdown.js":"RJXH/341Oa7csvj4pGRDfQ==","assets/touchswipe/jquery.touch-swipe.min.js":"9g/wVGnRdXmW2F9BctT/TQ==","assets/parallax/jarallax.min.js":"rX/x1RkUP0ZMvZZrsxrg7A==","assets/formstyler/jquery.formstyler.css":"ajjp8ztH9eVUk4rdhVGFYg==","assets/formstyler/jquery.formstyler.js":"Xv5CrVBApokt3elzzhEwuQ==","assets/formstyler/jquery.formstyler.min.js":"AZwL++bNUiLJxmlnInDaEQ==","assets/formstyler/jquery.formstyler.theme.css":"nnzXNu6YBQzXtwPVnmSyMQ==","assets/datepicker/jquery.datetimepicker.min.css":"ho+tif2BPmsXNeoVpuhDPg==","assets/datepicker/jquery.datetimepicker.full.js":"TcRSAGiGustgTlkirRSsRg==","assets/web/assets/mobirise-icons-bold/mobirise-icons-bold.css":"oCz4VsqVNHRevrgedUE3iA==","assets/web/assets/mobirise-icons-bold/mobirise-icons-bold.eot":"xL5gaCBkZEP9ksoDCgYMlg==","assets/web/assets/mobirise-icons-bold/mobirise-icons-bold.svg":"/6YZxrduGdMApfjQkLfW0g==","assets/web/assets/mobirise-icons-bold/mobirise-icons-bold.ttf":"My4xH5UmdimFH1eritsxVw==","assets/web/assets/mobirise-icons-bold/mobirise-icons-bold.woff":"4H/XculakPzhz3skasBxzg==","assets/socicon/css/styles.css":"yjHs7tV2SewoW36KZ0bi9w==","assets/socicon/fonts/socicon.eot":"MvYQV8XxgngrhGqjN3oHBw==","assets/socicon/fonts/socicon.svg":"U1iRKoyNjKeR+mUJr3QbXg==","assets/socicon/fonts/socicon.ttf":"IyAo3XNB2a/Q0ml3ZraPsQ==","assets/socicon/fonts/socicon.woff":"zQDjXd6bBUQi87pRsBWVqQ==","assets/socicon/fonts/socicon.woff2":"o3w8h99EHOwP99NXAoHpOQ==","assets/web/assets/mobirise-icons2/mobirise2.css":"+RO7OxVtE1FsD/N7V3/ADw==","assets/web/assets/mobirise-icons2/mobirise2.eot":"B2EjryGRojlTpzr1GHt3LQ==","assets/web/assets/mobirise-icons2/mobirise2.svg":"usCYAy7QdzckfeGReb9wWQ==","assets/web/assets/mobirise-icons2/mobirise2.ttf":"VMdAr7YYQ2ab9KiUyabAGA==","assets/web/assets/mobirise-icons2/mobirise2.woff":"xY3InaTfYGp0nlCuQBMudQ==","assets/formoid.min.js":"PCIvx4TB4BdNTxFrmRNOkQ==","assets/recaptcha.css":"rAr6hicA8NHvvo8fHdDrDQ==","assets/images/index-meta.png":"b6baOgAAfh4/X8c/zmosvA==","sw.js":"rUs5npuKZhM1B/LP9YXM7A==","assets/icons/512x512.png":"LDkgIQHHm3mojzA42sjvyw==","sw-connect.js":"LHdIp/pD3p2hapLzhfKvAA==","assets/web/assets/lazyload/lazyload.js":"thHIthe4L+TyjgJ1kTlT0A==","assets/images/imageedit-1_lr.png":"b6baOgAAfh4/X8c/zmosvA==","assets/images/dsc02218-595x446_lr.jpg":"72iGlKCvgXAhsMvTymobEA==","assets/images/mbr-595x397_lr.jpg":"L4RIHfFPsaW2pv0v8grNRg==","assets/images/dsc01039-2-2000x1125_lr.jpg":"wRHtKCsMEaDNyfHki4EpVQ==","assets/images/dsc01034-1462x823_lr.jpg":"GgswWhreLlmcjSFHAqL72A==","assets/images/dsc00378-2000x1125_lr.jpg":"LOgftLc/3qI0CtzLaWv4rw==","assets/images/index-meta_lr.png":"b6baOgAAfh4/X8c/zmosvA==","assets/icons/512x512_lr.png":"LDkgIQHHm3mojzA42sjvyw==","assets/images/dsc02248-3-643x362.jpeg":"ePi6ZR6shE14Tf6dpcqlAA==","assets/images/dsc02218-643x482.jpg":"brq+UsaRjbYX+zQfyRkIhA==","assets/images/dsc01019-643x482.jpg":"645sESuMHAWEhkR03/YDlA==","assets/images/dsc01021-643x482.jpg":"Jj3nW2ABxAmjXeQnlUXgSQ==","assets/images/dsc01028-643x482.jpg":"9894MErUVRr6eXE/wHkA/g==","assets/images/dsc02245-643x482.jpg":"oKE0GU2bFe9XU111p3YX/A==","assets/images/dsc01258-643x482.jpg":"TBxjvm/L9kmZngKo8rag1w==","assets/images/dsc02210-643x482.jpg":"6Xud5VPt0QIn+kUoODtQjw==","assets/images/dsc02248-3-643x362_lr.jpeg":"ePi6ZR6shE14Tf6dpcqlAA==","assets/images/dsc02218-643x482_lr.jpg":"brq+UsaRjbYX+zQfyRkIhA==","assets/images/dsc01019-643x482_lr.jpg":"645sESuMHAWEhkR03/YDlA==","assets/images/dsc01021-643x482_lr.jpg":"Jj3nW2ABxAmjXeQnlUXgSQ==","assets/images/dsc01028-643x482_lr.jpg":"9894MErUVRr6eXE/wHkA/g==","assets/images/dsc02245-643x482_lr.jpg":"oKE0GU2bFe9XU111p3YX/A==","assets/images/dsc01258-643x482_lr.jpg":"TBxjvm/L9kmZngKo8rag1w==","assets/images/dsc02210-643x482_lr.jpg":"6Xud5VPt0QIn+kUoODtQjw==","assets/FontAwesome/css/font-awesome.css":"MUQUl2Kv/7aja2ZwCX6jLw==","assets/FontAwesome/fonts/fontawesome-webfont.eot":"AW+kUDOpQv/srclw8i/kGw==","assets/FontAwesome/fonts/fontawesome-webfont.svg":"kS7GbXVy/4IXSTGTlkcL3g==","assets/FontAwesome/fonts/fontawesome-webfont.ttf":"7OvOOrlbZkCRm2svZrRL+A==","assets/FontAwesome/fonts/fontawesome-webfont.woff":"XgOIrq4WRpdzuM904tYwSw==","assets/FontAwesome/fonts/fontawesome-webfont.woff2":"2CmzIlHkI4BsqciqZAt9zw==","assets/FontAwesome/fonts/FontAwesome.otf":"ZjI216pEdiC2QQMtG3vlfA==","assets/images/mbr.png":"8c+e5xFLXszEP7VgZsD5NQ==","assets/images/mbr-4.png":"guNRf0+Qc4Bxj5yFVAsPsQ==","assets/images/mbr-2.png":"mYYa5Owa775Mvjn9S4LbEg==","assets/images/mbr-3.png":"CkbK0D4rf7TfSuRdHKg86Q==","assets/images/dsc02237.jpg":"x1z2ORdTYPIw9JTlZzPIZg==","assets/images/mbr_lr.png":"8c+e5xFLXszEP7VgZsD5NQ==","assets/images/mbr-4_lr.png":"guNRf0+Qc4Bxj5yFVAsPsQ==","assets/images/mbr-2_lr.png":"mYYa5Owa775Mvjn9S4LbEg==","assets/images/mbr-3_lr.png":"CkbK0D4rf7TfSuRdHKg86Q==","assets/images/dsc02237_lr.jpg":"x1z2ORdTYPIw9JTlZzPIZg==","assets/images/dsc02248-3.jpg":"4zDGWou1RrXsY5Vru8WUcw==","assets/images/dsc02248-3_lr.jpg":"4zDGWou1RrXsY5Vru8WUcw==","assets/images/gbg-test-hash.jpg":"lnwN4zQzYi0tP7hY82zN8Q==","assets/images/gbg-test-hash_lr.jpg":"lnwN4zQzYi0tP7hY82zN8Q==","assets/font-awesome-brands/../css/fontawesome.min.css":"PfCyez513n79gArx131WzA==","assets/font-awesome-brands/css/brands.min.css":"dJN5T1ExrC7eM/qNDV2mCw==","assets/font-awesome-brands/fonts/fa-brands-400.eot":"+4jg6xz0+tWGeLzYJl7gfw==","assets/font-awesome-brands/fonts/fa-brands-400.svg":"LxIkI3Xt1o6QE+z7WcZy6Q==","assets/font-awesome-brands/fonts/fa-brands-400.ttf":"jInfRywT+cff0/X8/qUerw==","assets/font-awesome-brands/fonts/fa-brands-400.woff":"ySJIJq3g43w0pFcHbrdswA==","assets/font-awesome-brands/fonts/fa-brands-400.woff2":"jPNmFiMZbC4f1UCUZZ8gOQ==","assets/font-awesome-solid/../css/fontawesome.min.css":"PfCyez513n79gArx131WzA==","assets/font-awesome-solid/css/solid.min.css":"HpmldUm/Kva7EwwmTek4oA==","assets/font-awesome-solid/fonts/fa-solid-900.eot":"AdwGQa3Wp/kP1giHO5scLw==","assets/font-awesome-solid/fonts/fa-solid-900.svg":"Zk3jky3WKRtLiowN28tMYQ==","assets/font-awesome-solid/fonts/fa-solid-900.ttf":"IO+jegHnejVos9by8kY66w==","assets/font-awesome-solid/fonts/fa-solid-900.woff":"h8tvVkjRVsTfnSKJz3c7AQ==","assets/font-awesome-solid/fonts/fa-solid-900.woff2":"tTHsbRPm6qyu0uf8dTKkAw==","assets/images/dsc02248-3.jpeg":"BvHiGmTpP4oXbN3k17Za3g==","assets/images/dsc02218.jpg":"SONSldejpA896zJkPAp4XQ==","assets/images/dsc01019.jpg":"SaKxk2Px2hWKUgNb+sjf3w==","assets/images/dsc01021.jpg":"2xvJ0fEeoB/WD7xB2Wq0xA==","assets/images/dsc01028.jpg":"2ccqMGCALlOFl0ag14glNw==","assets/images/dsc02245.jpg":"B+FkM639n+HTUXUkgev60w==","assets/images/dsc01258.jpg":"Ywe80vG+sYQPS1vJxb/iTw==","assets/images/dsc02210.jpg":"ooSTF4LQZ21quXwoIh0ZBg==","assets/images/dsc02248-3_lr.jpeg":"BvHiGmTpP4oXbN3k17Za3g==","assets/images/dsc02218_lr.jpg":"SONSldejpA896zJkPAp4XQ==","assets/images/dsc01019_lr.jpg":"SaKxk2Px2hWKUgNb+sjf3w==","assets/images/dsc01021_lr.jpg":"2xvJ0fEeoB/WD7xB2Wq0xA==","assets/images/dsc01028_lr.jpg":"2ccqMGCALlOFl0ag14glNw==","assets/images/dsc02245_lr.jpg":"B+FkM639n+HTUXUkgev60w==","assets/images/dsc01258_lr.jpg":"Ywe80vG+sYQPS1vJxb/iTw==","assets/images/dsc02210_lr.jpg":"ooSTF4LQZ21quXwoIh0ZBg==","assets/animatecss/animate.css":"fjruI/nrd0HOAeWn5UICJQ==","assets/viewportchecker/jquery.viewportchecker.js":"2t2kMxgGU03t28R+Gt4yMQ==","assets/images/popup.jpg":"ctiwRs6+GejhBVetNxn8NQ==","assets/popup-plugin/script.js":"lwMGKLS/CV2+T7V8ogfGXQ==","assets/popup-overlay-plugin/script.js":"z83QVk3OeWbUOXnxxooFPg==","assets/web/assets/mobirise-icons/mobirise-icons.css":"t/IrTIzfJvbDUoCV05F+7Q==","assets/web/assets/mobirise-icons/mobirise-icons.eot":"T9iJ+Vffe7n6Gk/+pf9gEw==","assets/web/assets/mobirise-icons/mobirise-icons.svg":"Yp5pSlGdnLgPdQLUa/Yv3w==","assets/web/assets/mobirise-icons/mobirise-icons.ttf":"r0OtN8kuMaYwUc+mlGDUWA==","assets/web/assets/mobirise-icons/mobirise-icons.woff":"3aYYVAIqADvsB1jjxJZ73w=="}}